_CharLS.cpython-310-darwin.so
jpeg_ls/_CharLS.pyx
jpeg_ls/data_io.py
jpeg_ls/__init__.py
jpeg_ls/define_charls_dll.h
jpeg_ls/example.py
jpeg_ls/CharLS.py
jpeg_ls/tests/test_decode.py
jpeg_ls/tests/__init__.py
jpeg_ls/tests/test_encode.py
jpeg_ls/tests/jlsimV100/TEST8R.PGM
jpeg_ls/tests/jlsimV100/TEST8G.PGM
jpeg_ls/tests/jlsimV100/README_IMG.TXT
jpeg_ls/tests/jlsimV100/T8C2E0.JLS
jpeg_ls/tests/jlsimV100/TEST8B.PGM
jpeg_ls/tests/jlsimV100/T8NDE0.JLS
jpeg_ls/tests/jlsimV100/T8C0E3.JLS
jpeg_ls/tests/jlsimV100/T8SSE0.JLS
jpeg_ls/tests/jlsimV100/T8C2E3.JLS
jpeg_ls/tests/jlsimV100/T8NDE3.JLS
jpeg_ls/tests/jlsimV100/T8C0E0.JLS
jpeg_ls/tests/jlsimV100/T8SSE3.JLS
jpeg_ls/tests/jlsimV100/T8C1E0.JLS
jpeg_ls/tests/jlsimV100/T8C1E3.JLS
jpeg_ls/tests/jlsimV100/TEST8.PPM
jpeg_ls/tests/jlsimV100/TEST16.PGM
jpeg_ls/tests/jlsimV100/T16E3.JLS
jpeg_ls/tests/jlsimV100/TEST8GR4.PGM
jpeg_ls/tests/jlsimV100/T16E0.JLS
jpeg_ls/tests/jlsimV100/TEST8BS2.PGM
pyjpegls-1.5.1.dist-info/RECORD
pyjpegls-1.5.1.dist-info/WHEEL
pyjpegls-1.5.1.dist-info/top_level.txt
pyjpegls-1.5.1.dist-info/METADATA
