Metadata-Version: 2.1
Name: pyjpegls
Version: 1.5.1
Summary: JPEG-LS for Python via CharLS C++ Library
Author: pydicom contributors
Author-email: "Pierre V. Villeneuve" <pierre.villeneuve@gmail.com>
License: MIT
Project-URL: documentation, https://pydicom.github.io/pydicom
Project-URL: download, https://github.com/pydicom/pyjpegls/archive/master.zip
Project-URL: homepage, https://github.com/pydicom/pyjpegls
Project-URL: repository, https://github.com/pydicom/pyjpegls
Keywords: python, jpeg
Classifier: License :: OSI Approved :: MIT License
Classifier: Development Status :: 5 - Production/Stable
Classifier: Natural Language :: English
Classifier: Programming Language :: Python
Classifier: Programming Language :: Python :: 3.9
Classifier: Programming Language :: Python :: 3.10
Classifier: Programming Language :: Python :: 3.11
Classifier: Programming Language :: Python :: 3.12
Classifier: Programming Language :: Python :: 3.13
Classifier: Programming Language :: Python :: Implementation :: CPython
Classifier: Operating System :: POSIX :: Linux
Classifier: Operating System :: MacOS
Classifier: Operating System :: Microsoft :: Windows
Classifier: Topic :: Software Development :: Libraries
Classifier: Topic :: File Formats
Classifier: Topic :: Scientific/Engineering :: Image Processing
Requires-Python: >=3.9
Requires-Dist: numpy>=2.0
